introspector/__init__.py
introspector/introspector.py
introspector/strict.py
introspector-0.2.1a0.dist-info/LICENSE
introspector-0.2.1a0.dist-info/METADATA
introspector-0.2.1a0.dist-info/WHEEL
introspector-0.2.1a0.dist-info/top_level.txt
introspector-0.2.1a0.dist-info/RECORD
