Metadata-Version: 2.1
Name: introspector
Version: 0.2.1a0
Summary: Introduce strict typing in your functions.
Home-page: https://github.com/Arthuchaut/introspector
Author: Arthuchaut
Author-email: arthuchaut@gmail.com
License: UNKNOWN
Project-URL: Bug Tracker, https://github.com/Arthuchaut/introspector/issues
Platform: UNKNOWN
Classifier: Programming Language :: Python :: 3
Classifier: License :: OSI Approved :: MIT License
Classifier: Operating System :: OS Independent
Requires-Python: >=3.10
License-File: LICENSE
